covidillness.py
covidillness-0.0.8.dist-info/METADATA
covidillness-0.0.8.dist-info/WHEEL
covidillness-0.0.8.dist-info/entry_points.txt
covidillness-0.0.8.dist-info/top_level.txt
covidillness-0.0.8.dist-info/RECORD
