Metadata-Version: 2.1
Name: covidillness
Version: 0.0.8
Summary: The graph of the number of ICU patients and cases due to Covid-19
Home-page: https://github.com/i-inose/covidillness
Author: Izuru Inose
Author-email: i.inose0304@gmail.com
Project-URL: Bug Tracker, https://github.com/i-inose/covidillness
Classifier: Programming Language :: Python :: 3
Classifier: License :: OSI Approved :: MIT License
Classifier: Operating System :: OS Independent
Requires-Python: >=3.7
